{
    "country": "US",
    "id": 54091,
    "language": "en-gl",
    "location": {
        "lat": 31.149952,
        "lon": -81.491486
    },
    "name": "Brunswick, GA",
    "search_volume": 7100,
    "slug": "brunswick-ga",
    "transportation_category": [
        "bus"
    ],
    "uuid": "dc763024-d7d3-42f8-9dbc-43c561edc4aa",
    "stations": [
        {
            "@context": "https://schema.org",
            "@type": "BusStop",
            "name": "Brunswick",
            "openingHours": "Mo-Su",
            "address": {
                "@type": "PostalAddress",
                "addressCountry": "United States",
                "addressLocality": "Brunswick, GA",
                "postalCode": "31523",
                "streetAddress": "2764 US Highway 17 S Unit 101"
            },
            "latitude": 31.1373,
            "longitude": -81.57118
        },
        {
            "@context": "https://schema.org",
            "@type": "BusStop",
            "name": "Brunswick (Perry Ln Rd/Venture Dr)",
            "openingHours": "Mo-Su",
            "address": {
                "@type": "PostalAddress",
                "addressCountry": "United States",
                "addressLocality": "Brunswick, GA",
                "postalCode": "31525",
                "streetAddress": "2360 Perry Lane Rd"
            },
            "latitude": 31.246053,
            "longitude": -81.507993
        }
    ]
}