{
    "country": "US",
    "id": 36511,
    "language": "en-gl",
    "location": {
        "lat": 44.564568,
        "lon": -123.26205
    },
    "name": "Corvallis, OR",
    "search_volume": 18300,
    "slug": "corvallis-or",
    "transportation_category": [
        "bus"
    ],
    "uuid": "10a293ec-3aa8-4ea3-aec2-96df4b859a54",
    "stations": [
        {
            "@context": "https://schema.org",
            "@type": "BusStop",
            "name": "Corvallis (Oregon State University - 14th St/Jefferson Way)",
            "openingHours": "Mo-Su",
            "address": {
                "@type": "PostalAddress",
                "addressCountry": "United States",
                "addressLocality": "Corvallis, OR",
                "postalCode": "97331",
                "streetAddress": "200 SW 15th St"
            },
            "latitude": 44.565111,
            "longitude": -123.2735
        },
        {
            "@context": "https://schema.org",
            "@type": "BusStop",
            "name": "Corvallis Bus Stop",
            "openingHours": "Mo-Su",
            "address": {
                "@type": "PostalAddress",
                "addressCountry": "United States",
                "addressLocality": "Corvallis, OR",
                "postalCode": "97333",
                "streetAddress": "100-198 Sw 5Th St"
            },
            "latitude": 44.564628,
            "longitude": -123.263103
        }
    ]
}