{
    "country": "US",
    "id": 20638,
    "language": "en-gl",
    "location": {
        "lat": 35.198284,
        "lon": -111.6513
    },
    "name": "Flagstaff, AZ",
    "search_volume": 29300,
    "slug": "flagstaff-az",
    "transportation_category": [
        "bus"
    ],
    "uuid": "fc0b7314-dbf8-4300-880b-4edaab118a60",
    "stations": [
        {
            "@context": "https://schema.org",
            "@type": "BusStop",
            "name": "Flagstaff Bus Station",
            "openingHours": "Mo-Su",
            "address": {
                "@type": "PostalAddress",
                "addressCountry": "United States",
                "addressLocality": "Flagstaff, AZ",
                "postalCode": "86001",
                "streetAddress": "880 E Butler Ave"
            },
            "latitude": 35.192248,
            "longitude": -111.639101
        },
        {
            "@context": "https://schema.org",
            "@type": "BusStop",
            "name": "Flagstaff Train Station",
            "openingHours": "Mo-Su",
            "address": {
                "@type": "PostalAddress",
                "addressCountry": "United States",
                "addressLocality": "Flagstaff, AZ",
                "postalCode": "86001",
                "streetAddress": "1 E Rte 66"
            },
            "latitude": 35.197635,
            "longitude": -111.649931
        }
    ]
}