{
    "country": "US",
    "id": 22768,
    "language": "en-gl",
    "location": {
        "lat": 34.14251,
        "lon": -118.25507
    },
    "name": "Glendale, CA",
    "search_volume": 3000,
    "slug": "glendale-ca",
    "transportation_category": [
        "bus"
    ],
    "uuid": "d608887f-e4cc-419c-99df-4fdb5383d99c",
    "stations": [
        {
            "@context": "https://schema.org",
            "@type": "BusStop",
            "name": "Glendale Train Station",
            "openingHours": "Mo-Su",
            "address": {
                "@type": "PostalAddress",
                "addressCountry": "United States",
                "addressLocality": "Glendale, CA",
                "postalCode": "91204",
                "streetAddress": "400 W Cerritos Ave"
            },
            "latitude": 34.123639,
            "longitude": -118.259027
        }
    ]
}