{
    "country": "US",
    "id": 54981,
    "language": "en-gl",
    "location": {
        "lat": 27.901413,
        "lon": -81.58591
    },
    "name": "Lake Wales, FL",
    "search_volume": 800,
    "slug": "lake-wales-fl",
    "transportation_category": [
        "bus"
    ],
    "uuid": "ecb8bbcf-da42-4dbf-ac9d-d004b1bc6666",
    "stations": [
        {
            "@context": "https://schema.org",
            "@type": "BusStop",
            "name": "Lake Wales (Citgo Gas)",
            "openingHours": "Mo-Su",
            "address": {
                "@type": "PostalAddress",
                "addressCountry": "United States",
                "addressLocality": "Lake Wales, FL",
                "postalCode": "33853",
                "streetAddress": "20500 US Hwy 27"
            },
            "latitude": 27.913752,
            "longitude": -81.603937
        }
    ]
}