{
    "country": "US",
    "id": 55401,
    "language": "en-gl",
    "location": {
        "lat": 38.965725,
        "lon": -76.88025
    },
    "name": "New Carrollton, MD",
    "search_volume": 9400,
    "slug": "new-carrollton-md",
    "transportation_category": [
        "bus"
    ],
    "uuid": "1315e401-5aa8-4133-a70a-2bf520996248",
    "stations": [
        {
            "@context": "https://schema.org",
            "@type": "BusStop",
            "name": "New Carrollton Bus Stop",
            "openingHours": "Mo-Su",
            "address": {
                "@type": "PostalAddress",
                "addressCountry": "United States",
                "addressLocality": "New Carrollton, MD",
                "postalCode": "20785",
                "streetAddress": "4700 Garden City Dr"
            },
            "latitude": 38.946977,
            "longitude": -76.872411
        }
    ]
}