{
    "country": "US",
    "id": 36601,
    "language": "en-gl",
    "location": {
        "lat": 47.252876,
        "lon": -122.44429
    },
    "name": "Tacoma, WA",
    "search_volume": 25600,
    "slug": "tacoma-wa",
    "transportation_category": [
        "bus"
    ],
    "uuid": "391fdb5b-d2dd-4560-a709-920de84ade6d",
    "stations": [
        {
            "@context": "https://schema.org",
            "@type": "BusStop",
            "name": "Tacoma (G St & Puyallup Ave)",
            "openingHours": "Mo-Su",
            "address": {
                "@type": "PostalAddress",
                "addressCountry": "United States",
                "addressLocality": "Tacoma, WA",
                "postalCode": "98421",
                "streetAddress": "2499 E G St"
            },
            "latitude": 47.240512,
            "longitude": -122.424745
        },
        {
            "@context": "https://schema.org",
            "@type": "BusStop",
            "name": "Tacoma Bus Station",
            "openingHours": "Mo-Su",
            "address": {
                "@type": "PostalAddress",
                "addressCountry": "United States",
                "addressLocality": "Tacoma, WA",
                "postalCode": "98402",
                "streetAddress": "510 Puyallup Ave"
            },
            "latitude": 47.240786,
            "longitude": -122.42765
        }
    ]
}